{
  "contratos": [
    {
      "contratante": {
        "empresa": "Irmãos Gonçalves",
        "cnpj": "76820757",
        "rua": "Avenida Jorje Texeira",
        "numero": "123",
        "estado": "Rondônia",
        "cidade": "Jaru"
      },
      "contratado": {
        "empresa": "Distribuidora Coimbra",
        "cnpj": "76820757",
        "rua": "Avenida Sete de Setembro",
        "numero": "156",
        "estado": "Rondônia",
        "cidade": "Porto Velho"
      },
      "tipoContrato": "Arrendamento",
      "carencia": "Alguma Coisa",
      "valor": "100000",
      "parcelas": "5",
      "inicioVigencia": "2023-10-18",
      "finalVigencia": "2024-10-17",
      "key": "ad8bb758-04ed-4531-b1a1-1eefaaeb63bc"
    },
    {
      "contratante": {
        "empresa": "Irmãos Gonçalves",
        "cnpj": "76820757",
        "rua": "Avenida Jorje Texeira",
        "numero": "123",
        "estado": "Rondônia",
        "cidade": "Jaru"
      },
      "contratado": {
        "empresa": "Barbosa Materiais Elétricos e Hidráulicos",
        "cnpj": "76820757",
        "rua": "Avenida Sete de Setembro",
        "numero": "156",
        "estado": "Rondônia",
        "cidade": "Porto Velho"
      },
      "tipoContrato": "Arrendamento",
      "carencia": "Alguma Coisa",
      "valor": "100000",
      "parcelas": "5",
      "inicioVigencia": "2023-10-18",
      "finalVigencia": "2024-10-17",
      "key": "ad8bb758-04ed-4531-b1a1-1eefaaeb63bc"
    },
    {
      "contratante": {
        "empresa": "Magazine Luiza",
        "cnpj": "76820757",
        "rua": "Avenida Jorje Texeira",
        "numero": "123",
        "estado": "Rondônia",
        "cidade": "Jaru"
      },
      "contratado": {
        "empresa": "Distribuidora Coimbra",
        "cnpj": "76820757",
        "rua": "Avenida Sete de Setembro",
        "numero": "156",
        "estado": "Rondônia",
        "cidade": "Porto Velho"
      },
      "tipoContrato": "Arrendamento",
      "carencia": "Alguma Coisa",
      "valor": "100000",
      "parcelas": "5",
      "inicioVigencia": "2023-10-18",
      "finalVigencia": "2024-10-17",
      "key": "ad8bb758-04ed-4531-b1a1-1eefaaeb63bc"
    },
    {
      "contratante": {
        "empresa": "Americanas",
        "cnpj": "76820757",
        "rua": "Avenida Jorje Texeira",
        "numero": "123",
        "estado": "Rondônia",
        "cidade": "Jaru"
      },
      "contratado": {
        "empresa": "Distribuidora Coimbra",
        "cnpj": "76820757",
        "rua": "Avenida Sete de Setembro",
        "numero": "156",
        "estado": "Rondônia",
        "cidade": "Porto Velho"
      },
      "tipoContrato": "Locação de Serviços",
      "carencia": "Alguma Coisa",
      "valor": "100000",
      "parcelas": "5",
      "inicioVigencia": "2023-10-18",
      "finalVigencia": "2024-10-17",
      "key": "ad8bb758-04ed-4531-b1a1-1eefaaeb63bc"
    }
  ]
}